LICENSE
MANIFEST.in
README.md
setup.cfg
setup.py
django_mp_slider.egg-info/PKG-INFO
django_mp_slider.egg-info/SOURCES.txt
django_mp_slider.egg-info/dependency_links.txt
django_mp_slider.egg-info/top_level.txt
slider/__init__.py
slider/admin.py
slider/models.py
slider/locale/ru/LC_MESSAGES/django.mo
slider/locale/ru/LC_MESSAGES/django.po
slider/locale/uk/LC_MESSAGES/django.mo
slider/locale/uk/LC_MESSAGES/django.po
slider/migrations/0001_initial.py
slider/migrations/__init__.py
slider/static/slider/slideshow.css
slider/templates/slider.html
slider/templates/slideshow.html
slider/templatetags/__init__.py
slider/templatetags/slider.py