Metadata-Version: 2.1
Name: django-mp-slider
Version: 1.0.0
Summary: Django slider app
Home-page: https://github.com/pmaigutyak/mp-slider
Author: Paul Maigutyak
Author-email: pmaigutyak@gmail.com
License: MIT
Download-URL: https://github.com/pmaigutyak/mp-slider/archive/1.0.0.tar.gz
Platform: UNKNOWN
License-File: LICENSE
